alexflow/__init__.py
alexflow/core.py
alexflow/helper.py
alexflow/adapters/__init__.py
alexflow/adapters/executor/__init__.py
alexflow/adapters/executor/_reference_manager.py
alexflow/adapters/executor/alexflow.py
alexflow/adapters/executor/luigi.py
alexflow/adapters/output/__init__.py
alexflow/adapters/output/h5store.py
alexflow/adapters/storage/__init__.py
alexflow/adapters/storage/composite_storage.py
alexflow/adapters/storage/core.py
alexflow/adapters/storage/local_storage.py
alexflow/coreml/__init__.py
alexflow/coreml/dataset.py
alexflow/coreml/prediction.py
alexflow/coreml/tasks.py
alexflow/misc/__init__.py
alexflow/misc/gjson.py
alexflow/testing/__init__.py
alexflow/testing/tasks.py
alexflow-1.1.4.dist-info/METADATA
alexflow-1.1.4.dist-info/WHEEL
alexflow-1.1.4.dist-info/top_level.txt
alexflow-1.1.4.dist-info/RECORD
