Metadata-Version: 2.1
Name: alexflow
Version: 1.1.4
Summary: ALEXFlow is a python workflow library built for reproducible complex workflow
Home-page: https://github.com/AlpacaDB/alexflow.git
Author: Sho Yoshida
Author-email: yoshiso@alpaca.ai
License: MIT
Platform: UNKNOWN
Classifier: License :: OSI Approved :: MIT License
Classifier: Programming Language :: Python :: 3
Classifier: Programming Language :: Python :: 3.7
Classifier: Programming Language :: Python :: 3.8
Requires-Python: >=3.7
Requires-Dist: pandas
Requires-Dist: numpy
Requires-Dist: dataclass-serializer (>=1.3.1)
Requires-Dist: multiprocess
Requires-Dist: joblib
Requires-Dist: cached-property
